microSWIFT/__init__.py
microSWIFT/checkout.py
microSWIFT/microSWIFT.py
microSWIFT/version.py
microSWIFT/accoutrements/__init__.py
microSWIFT/accoutrements/adafruit_fxas21002c.py
microSWIFT/accoutrements/adafruit_fxos8700.py
microSWIFT/accoutrements/gps_module.py
microSWIFT/accoutrements/imu_module.py
microSWIFT/accoutrements/sbd.py
microSWIFT/accoutrements/telemetry_stack.py
microSWIFT/data/EJs-MacBook-Pro.local_IMU_14Dec2022_203834UTC.dat
microSWIFT/data/EJs-MacBook-Pro.local_IMU_14Dec2022_212350UTC.dat
microSWIFT/mocks/__init__.py
microSWIFT/mocks/mock_adafruit_fxas21002c.py
microSWIFT/mocks/mock_adafruit_fxos8700.py
microSWIFT/mocks/mock_board.py
microSWIFT/mocks/mock_busio.py
microSWIFT/mocks/mock_rpi_gpio.py
microSWIFT/mocks/mock_serial.py
microSWIFT/processing/__init__.py
microSWIFT/processing/collate_imu_and_gps.py
microSWIFT/processing/gps_waves.py
microSWIFT/processing/integrate_imu.py
microSWIFT/processing/transform_imu.py
microSWIFT/processing/uvza_waves.py
microSWIFT/tests/__init__.py
microSWIFT/tests/test_checkout.py
microSWIFT/tests/test_configuration.py
microSWIFT/tests/test_gps_checkout.py
microSWIFT/tests/test_imu.py
microSWIFT/tests/test_microSWIFT.py
microSWIFT/tests/test_mock_adafruit_fxas21002c.py
microSWIFT/tests/test_mock_adafruit_fxos8700.py
microSWIFT/tests/test_mock_board.py
microSWIFT/tests/test_mock_busio.py
microSWIFT/tests/test_mock_rpi_gpio.py
microSWIFT/tests/test_mock_serial.py
microSWIFT/utils/__init__.py
microSWIFT/utils/configuration.py
microSWIFT/utils/log.py
microSWIFT/utils/utils.py
microSWIFT-0.0.dev0.dist-info/LICENSE.md
microSWIFT-0.0.dev0.dist-info/METADATA
microSWIFT-0.0.dev0.dist-info/WHEEL
microSWIFT-0.0.dev0.dist-info/top_level.txt
microSWIFT-0.0.dev0.dist-info/RECORD
