Metadata-Version: 2.1
Name: microSWIFT
Version: 0.0.dev0
Summary: microSWIFT: The main operational software that runs on the                microSWIFT V1 wave buoys.
Home-page: https://github.com/SASlabgroup/microSWIFT
Download-URL: 
Author: SASlabgroup
Author-email: jthomson@apl.washington.edu
Maintainer: SASlabgroup
Maintainer-email: jthomson@apl.washington.edu
License: MIT
Platform: OS Independent
Classifier: Intended Audience :: Science/Research
Classifier: License :: OSI Approved :: MIT License
Classifier: Programming Language :: Python :: 3
Classifier: Topic :: Scientific/Engineering
Requires: numpy
Requires: pynmea2
Requires-Python: >= 3.7
License-File: LICENSE.md
Requires-Dist: numpy
Requires-Dist: pynmea2
